giotto_bottleneck.cpython-35m-x86_64-linux-gnu.so
giotto_cubical_complex.cpython-35m-x86_64-linux-gnu.so
giotto_persistent_cohomology.cpython-35m-x86_64-linux-gnu.so
giotto_ripser.cpython-35m-x86_64-linux-gnu.so
giotto_simplex_tree.cpython-35m-x86_64-linux-gnu.so
giotto_wasserstein.cpython-35m-x86_64-linux-gnu.so
giotto/__init__.py
giotto/_version.py
giotto/base.py
giotto/pipeline.py
giotto/diagrams/__init__.py
giotto/diagrams/_metrics.py
giotto/diagrams/_utils.py
giotto/diagrams/distance.py
giotto/diagrams/features.py
giotto/diagrams/preprocessing.py
giotto/diagrams/tests/__init__.py
giotto/diagrams/tests/test_distance.py
giotto/diagrams/tests/test_features.py
giotto/diagrams/tests/test_preprocessing.py
giotto/externals/__init__.py
giotto/externals/python/__init__.py
giotto/externals/python/cubical_complex_interface.py
giotto/externals/python/ripser_interface.py
giotto/externals/python/simplex_tree_interface.py
giotto/graphs/__init__.py
giotto/graphs/create_clique_complex.py
giotto/graphs/geodesic_distance.py
giotto/graphs/graph_entropy.py
giotto/graphs/heat_diffusion.py
giotto/graphs/kneighbors.py
giotto/graphs/transition.py
giotto/graphs/tests/__init__.py
giotto/graphs/tests/test_create_complex.py
giotto/graphs/tests/test_geodesic_distance.py
giotto/graphs/tests/test_graph_entropy.py
giotto/graphs/tests/test_heat_diffusion.py
giotto/graphs/tests/test_kneighbors.py
giotto/graphs/tests/test_transition.py
giotto/homology/__init__.py
giotto/homology/_utils.py
giotto/homology/consistent.py
giotto/homology/point_clouds.py
giotto/homology/tests/__init__.py
giotto/homology/tests/test_consistent.py
giotto/homology/tests/test_point_clouds.py
giotto/mapper/__init__.py
giotto/mapper/cluster.py
giotto/mapper/cover.py
giotto/mapper/filter.py
giotto/mapper/nerve.py
giotto/mapper/pipeline.py
giotto/mapper/visualization.py
giotto/mapper/utils/__init__.py
giotto/mapper/utils/_cluster.py
giotto/mapper/utils/_cover.py
giotto_learn_nightly-20191220.25.dist-info/METADATA
giotto_learn_nightly-20191220.25.dist-info/RECORD
giotto_learn_nightly-20191220.25.dist-info/WHEEL
giotto_learn_nightly-20191220.25.dist-info/top_level.txt
